Metadata-Version: 2.4
Name: fixit-cli-tool
Version: 1.0.0
Summary: Cross-platform software installation framework
Home-page: https://github.com/Jayu1214/fixit
Author: FixIt Team
Author-email: team@fixit.dev
Project-URL: Bug Reports, https://github.com/Jayu1214/fixit/issues
Project-URL: Source, https://github.com/Jayu1214/fixit
Project-URL: Documentation, https://github.com/Jayu1214/fixit/wiki
Classifier: Development Status :: 4 - Beta
Classifier: Intended Audience :: Developers
Classifier: Intended Audience :: System Administrators
Classifier: Topic :: System :: Installation/Setup
Classifier: Topic :: System :: Software Distribution
Classifier: License :: OSI Approved :: MIT License
Classifier: Programming Language :: Python :: 3
Classifier: Programming Language :: Python :: 3.8
Classifier: Programming Language :: Python :: 3.9
Classifier: Programming Language :: Python :: 3.10
Classifier: Programming Language :: Python :: 3.11
Classifier: Programming Language :: Python :: 3.12
Classifier: Programming Language :: Python :: 3.13
Classifier: Operating System :: OS Independent
Classifier: Operating System :: Microsoft :: Windows
Classifier: Operating System :: POSIX :: Linux
Classifier: Operating System :: MacOS
Requires-Python: >=3.8
License-File: LICENSE
Requires-Dist: requests>=2.31.0
Requires-Dist: colorama>=0.4.6
Requires-Dist: tqdm>=4.66.0
Requires-Dist: packaging>=23.1
Dynamic: author
Dynamic: author-email
Dynamic: classifier
Dynamic: description
Dynamic: description-content-type
Dynamic: home-page
Dynamic: license-file
Dynamic: project-url
Dynamic: requires-dist
Dynamic: requires-python
Dynamic: summary
